pyPhix-0.1.dist-info/METADATA
pyPhix-0.1.dist-info/RECORD
pyPhix-0.1.dist-info/WHEEL
pyPhix-0.1.dist-info/top_level.txt
pyphix/__init__.py
pyphix/fix.py
pyphix/generalutil.py
pyphix/io.py
