Metadata-Version: 2.1
Name: pyPhix
Version: 0.1
Summary: The Python Fixed Point module
Home-page: https://github.com/sfavazza/pyphix
Author: Samuele Favazza
Author-email: sfavazza.github@gmail.com
License: UNKNOWN
Platform: UNKNOWN
Classifier: Development Status :: 5 - Production/Stable
Classifier: Intended Audience :: Developers
Classifier: Intended Audience :: Science/Research
Classifier: License :: OSI Approved :: Mozilla Public License 2.0 (MPL 2.0)
Classifier: Operating System :: OS Independent
Classifier: Programming Language :: Python :: 3.6
Classifier: Topic :: Scientific/Engineering
Requires-Dist: numpy
